AdvEMDpy/AdvEMDpy.py
AdvEMDpy/CASE_STUDY_carbon_dioxide_and_carbon_etf.py
AdvEMDpy/CASE_STUDY_human_mortality_database_death_rate.py
AdvEMDpy/CASE_STUDY_human_mortality_database_monthly_birth_rate.py
AdvEMDpy/CASE_STUDY_noise.py
AdvEMDpy/README_images.py
AdvEMDpy/__init__.py
AdvEMDpy/aas_figures_replication_script.py
AdvEMDpy/emd_basis.py
AdvEMDpy/emd_experimental.py
AdvEMDpy/emd_hilbert.py
AdvEMDpy/emd_mean.py
AdvEMDpy/emd_preprocess.py
AdvEMDpy/emd_unit_test.py
AdvEMDpy/emd_utils.py
AdvEMDpy-0.0.15.dist-info/LICENSE
AdvEMDpy-0.0.15.dist-info/METADATA
AdvEMDpy-0.0.15.dist-info/WHEEL
AdvEMDpy-0.0.15.dist-info/top_level.txt
AdvEMDpy-0.0.15.dist-info/RECORD
